README.md
setup.py
SAMITorch.egg-info/PKG-INFO
SAMITorch.egg-info/SOURCES.txt
SAMITorch.egg-info/dependency_links.txt
SAMITorch.egg-info/requires.txt
SAMITorch.egg-info/top_level.txt
samitorch/__init__.py
samitorch/configs/__init__.py
samitorch/configs/configurations.py
samitorch/initializers/__init__.py
samitorch/initializers/initializers.py
samitorch/inputs/__init__.py
samitorch/inputs/batch.py
samitorch/inputs/datasets.py
samitorch/inputs/images.py
samitorch/inputs/patch.py
samitorch/inputs/sample.py
samitorch/inputs/transformers.py
samitorch/inputs/utils.py
samitorch/models/__init__.py
samitorch/models/layers.py
samitorch/models/resnet3d.py
samitorch/models/unet3d.py
samitorch/parsers/__init__.py
samitorch/parsers/parsers.py
samitorch/preprocessing/__init__.py
samitorch/preprocessing/pipelines.py
samitorch/utils/__init__.py
samitorch/utils/files.py
samitorch/utils/slice_builder.py
samitorch/utils/tensors.py
tests/data/__init__.py
tests/factories/__init__.py
tests/factories/test_dataset_factory.py
tests/factories/test_layer_factories.py
tests/inputs/__init__.py
tests/inputs/test_dataloaders.py
tests/inputs/test_transformers.py
tests/models/__init__.py
tests/models/model_helper_test.py
tests/models/test_resnet3d.py
tests/models/test_unet3d.py
tests/preprocessing/__init__.py
tests/utils/__init__.py
tests/utils/test_parsers.py
tests/utils/test_utils.py