Metadata-Version: 2.1
Name: SAMITorch
Version: 0.2.5
Summary: Deep Learning Framework For Medical Image Analysis
Home-page: UNKNOWN
Author: Benoit Anctil-Robitaille and Pierre-Luc Delisle
Author-email: benoit.anctil-robitaille.1@ens.etsmtl.ca
License: MIT
Platform: UNKNOWN
Classifier: License :: OSI Approved :: MIT License
Classifier: Programming Language :: Python :: 3
Classifier: Programming Language :: Python :: 3.7
